ip6w/__init__.py
ip6w/src/__init__.py
ip6w/src/__main__.py
ip6w/src/ip6words.py
ip6w/src/ip_handling.py
ip6w/src/iwords.py
ip6w/src/words.dill
ip6words-1.1.5.dist-info/DESCRIPTION.rst
ip6words-1.1.5.dist-info/METADATA
ip6words-1.1.5.dist-info/RECORD
ip6words-1.1.5.dist-info/WHEEL
ip6words-1.1.5.dist-info/entry_points.txt
ip6words-1.1.5.dist-info/metadata.json
ip6words-1.1.5.dist-info/top_level.txt
